tno/quantum/ml/__init__.py
tno/quantum/ml/py.typed
tno/quantum/ml/test/__init__.py
tno/quantum/ml/test/test_ml.py
tno_quantum_ml-1.1.0.dist-info/licenses/LICENSE
tno_quantum_ml-1.1.0.dist-info/METADATA
tno_quantum_ml-1.1.0.dist-info/WHEEL
tno_quantum_ml-1.1.0.dist-info/top_level.txt
tno_quantum_ml-1.1.0.dist-info/RECORD
